gpputils/__init__.py
gpputils/gpputils.py
gpputils-0.1.0.dist-info/AUTHORS.rst
gpputils-0.1.0.dist-info/LICENSE
gpputils-0.1.0.dist-info/METADATA
gpputils-0.1.0.dist-info/WHEEL
gpputils-0.1.0.dist-info/top_level.txt
gpputils-0.1.0.dist-info/RECORD
