Metadata-Version: 2.1
Name: gpputils
Version: 0.1.0
Summary: Utility functions for GPP R&D
Home-page: https://github.com/gpp-rnd/gpputils
Author: Mudra Hegde
Author-email: mhegde@broadinstitute.org
License: MIT license
Keywords: gpputils
Platform: UNKNOWN
Classifier: Development Status :: 2 - Pre-Alpha
Classifier: Intended Audience :: Developers
Classifier: License :: OSI Approved :: MIT License
Classifier: Natural Language :: English
Classifier: Programming Language :: Python :: 3
Classifier: Programming Language :: Python :: 3.5
Classifier: Programming Language :: Python :: 3.6
Classifier: Programming Language :: Python :: 3.7
Classifier: Programming Language :: Python :: 3.8
Requires-Python: >=3.5
